.gitattributes
.gitignore
LICENSE
MANIFEST.in
README-teams.md
README.md
deploy.bat
deploy.sh
localdeploy.bat
requirements.tests.txt
requirements.txt
setup.cfg
setup.py
utilita/net/__init__.py
utilita/net/db/__init__.py
utilita/net/db/db.py
utilita/net/gcshelper/__init__.py
utilita/net/gcshelper/gcshelper.py
utilita/net/microsofthelper/__init__.py
utilita/net/microsofthelper/auth.py
utilita/net/microsofthelper/constants.py
utilita/net/microsofthelper/log.py
utilita/net/microsofthelper/sharepoint.py
utilita/net/microsofthelper/teams.py
utilita/net/scripts/init_microsofthelper.py
utilita/net/sftphelper/sftphelper.py
utilita_net.egg-info/PKG-INFO
utilita_net.egg-info/SOURCES.txt
utilita_net.egg-info/dependency_links.txt
utilita_net.egg-info/entry_points.txt
utilita_net.egg-info/requires.txt
utilita_net.egg-info/top_level.txt