Metadata-Version: 2.4
Name: utilita-net
Version: 0.0.9
Summary: utilita but with helpers for web services
Home-page: https://github.com/trtrojo
Download-URL: https://github.com/trtrojo
Author: Tommy Rojo
Author-email: tr.trojo@gmail.com
License: MIT
Classifier: Development Status :: 3 - Alpha
Classifier: Intended Audience :: Developers
Classifier: Topic :: Utilities
Classifier: License :: OSI Approved :: MIT License
Classifier: Programming Language :: Python :: 3.8
License-File: LICENSE
Requires-Dist: msal>=1.24.1
Requires-Dist: requests>=2.25.0
Requires-Dist: google-cloud-pubsub>=2.7.0
Requires-Dist: google-cloud-storage>=1.41.1
Requires-Dist: google-auth
Dynamic: author
Dynamic: author-email
Dynamic: classifier
Dynamic: download-url
Dynamic: home-page
Dynamic: license
Dynamic: license-file
Dynamic: requires-dist
Dynamic: summary
